scdataset/__init__.py
scdataset/multiindexable.py
scdataset/scdataset.py
scdataset/strategy.py
scdataset/transforms.py
scdataset/experimental/__init__.py
scdataset/experimental/auto_config.py
scdataset-0.3.0.dist-info/licenses/LICENSE
scdataset-0.3.0.dist-info/METADATA
scdataset-0.3.0.dist-info/WHEEL
scdataset-0.3.0.dist-info/top_level.txt
scdataset-0.3.0.dist-info/RECORD
