Metadata-Version: 2.4
Name: scDataset
Version: 0.3.0
Summary: Scalable Data Loading for Deep Learning on Large-Scale Single-Cell Omics
Author-email: Davide D'Ascenzo <davide.dascenzo.work@gmail.com>
License: MIT License
Project-URL: Homepage, https://github.com/scDataset/scDataset
Project-URL: Issues, https://github.com/scDataset/scDataset/issues
Project-URL: Documentation, https://scdataset.github.io/
Classifier: Programming Language :: Python :: 3
Classifier: License :: OSI Approved :: MIT License
Classifier: Operating System :: OS Independent
Requires-Python: >=3.8
License-File: LICENSE
Requires-Dist: numpy>=1.17.0
Requires-Dist: torch>=1.2.0
Provides-Extra: dev
Requires-Dist: pytest>=7.0.0; extra == "dev"
Requires-Dist: pytest-cov>=4.0.0; extra == "dev"
Requires-Dist: pre-commit>=3.0.0; extra == "dev"
Requires-Dist: ruff>=0.8.0; extra == "dev"
Provides-Extra: docs
Requires-Dist: sphinx>=5.0.0; extra == "docs"
Requires-Dist: sphinx-book-theme>=1.0.0; extra == "docs"
Requires-Dist: sphinx-sitemap>=2.5.0; extra == "docs"
Requires-Dist: nbsphinx>=0.9.0; extra == "docs"
Requires-Dist: pandoc>=2.0.0; extra == "docs"
Provides-Extra: auto
Requires-Dist: psutil>=5.0.0; extra == "auto"
Dynamic: license-file
